ping_before_wakeonlan/__init__.py
ping_before_wakeonlan/cmd.py
ping_before_wakeonlan-1.0.2.dist-info/licenses/LICENSE
ping_before_wakeonlan-1.0.2.dist-info/METADATA
ping_before_wakeonlan-1.0.2.dist-info/WHEEL
ping_before_wakeonlan-1.0.2.dist-info/entry_points.txt
ping_before_wakeonlan-1.0.2.dist-info/top_level.txt
ping_before_wakeonlan-1.0.2.dist-info/RECORD
