Metadata-Version: 2.4
Name: ping-before-wakeonlan
Version: 1.0.2
Summary: Meet this Python Wake-on-LAN (WOL) Tool! It smartly checks your device status with integrated ping before sending the magic packet, ensuring efficiency. Set max wake devices, prevent power surges.
Home-page: https://github.com/changyy/ping-before-wakeonlan
Download-URL: https://pypi.org/project/ping-before-wakeonlan/
Author: Yuan-Yi Chang
Author-email: <changyy.csie@gmail.com>
Keywords: python,ping,wol
Classifier: Programming Language :: Python :: 3
Classifier: Operating System :: MacOS :: MacOS X
Requires-Python: >=3.10
License-File: LICENSE
Dynamic: author
Dynamic: author-email
Dynamic: classifier
Dynamic: description
Dynamic: description-content-type
Dynamic: download-url
Dynamic: home-page
Dynamic: keywords
Dynamic: license-file
Dynamic: requires-python
Dynamic: summary
